README.md
setup.py
simcli/__init__.py
simcli.egg-info/PKG-INFO
simcli.egg-info/SOURCES.txt
simcli.egg-info/dependency_links.txt
simcli.egg-info/not-zip-safe
simcli.egg-info/top_level.txt