Metadata-Version: 1.1
Name: simcli
Version: 0.1.1
Summary: SimpleCli class implementation which can be used to make CLI based utilities
Home-page: https://bitbucket.org/deniskhodus/simcli
Author: Denis Khodus
Author-email: deniskhodus@gmail.com
License: MIT
Keywords: cli python
Platform: UNKNOWN
Classifier: Development Status :: 5 - Production/Stable
Classifier: License :: OSI Approved :: Mozilla Public License 2.0 (MPL 2.0)
Classifier: Programming Language :: Python :: 2
Classifier: Programming Language :: Python :: 3
Classifier: Topic :: Software Development
Classifier: Topic :: Software Development :: Libraries
Classifier: Topic :: Software Development :: Libraries :: Python Modules
